stactools/gap/__init__.py
stactools/gap/commands.py
stactools/gap/constants.py
stactools/gap/metadata.py
stactools/gap/stac.py
stactools/gap/utils.py
stactools_gap-0.1.0.dist-info/LICENSE
stactools_gap-0.1.0.dist-info/METADATA
stactools_gap-0.1.0.dist-info/WHEEL
stactools_gap-0.1.0.dist-info/top_level.txt
stactools_gap-0.1.0.dist-info/RECORD
