Metadata-Version: 2.1
Name: stactools-gap
Version: 0.1.0
Summary: stactools package for working with USGS Gap Analysis Project (GAP) data
Home-page: https://github.com/stactools-gaps/stactools-gap
Author: stac-utils
Author-email: stac@radiant.earth
License: UNKNOWN
Project-URL: Documentation, https://stactools-gap.readthedocs.io/en/latest/
Project-URL: Issues, https://github.com/stactools-gaps/gap/issues
Keywords: stactools,pystac,catalog,STAC
Platform: UNKNOWN
Classifier: Development Status :: 4 - Beta
Classifier: License :: OSI Approved :: Apache Software License
Classifier: Programming Language :: Python :: 3.6
Classifier: Programming Language :: Python :: 3.7
Classifier: Programming Language :: Python :: 3.8
Classifier: Programming Language :: Python :: 3.9
License-File: LICENSE
Requires-Dist: stactools (==0.2.1a1)
